chapter10/__init__.py
chapter10/analog.py
chapter10/arinc429.py
chapter10/c10.py
chapter10/computer.py
chapter10/discrete.py
chapter10/ethernet.py
chapter10/i1394.py
chapter10/image.py
chapter10/message.py
chapter10/ms1553.py
chapter10/packet.py
chapter10/parallel.py
chapter10/pcm.py
chapter10/time.py
chapter10/uart.py
chapter10/util.py
chapter10/video.py
pychapter10-1.1.19.dist-info/WHEEL
pychapter10-1.1.19.dist-info/METADATA
pychapter10-1.1.19.dist-info/LICENSE.txt
pychapter10-1.1.19.dist-info/RECORD
