Metadata-Version: 2.1
Name: pychapter10
Version: 1.1.19
Summary: A parser library for the IRIG 106 Chapter 10 data format.
License: UNKNOWN
Author-email: Micah Ferrill <ferrillm@avtest.com>
Requires-Python: >=3.6
Classifier: Development Status :: 5 - Production/Stable
Classifier: Intended Audience :: Developers
Classifier: License :: OSI Approved :: BSD License
Classifier: Operating System :: OS Independent
Classifier: Programming Language :: Python :: 3
Classifier: Programming Language :: Python :: 3 :: Only
Classifier: Programming Language :: Python :: 3.7
Classifier: Programming Language :: Python :: 3.8
Classifier: Programming Language :: Python :: 3.9
Classifier: Topic :: Software Development :: Libraries
Requires-Dist: bitstring>=3.1.7
Requires-Dist: bitstruct==8.11.0
Requires-Dist: editables>=0.2
Provides-Extra: docs
Requires-Dist: sphinx>=2.4.4; extra == "docs"
Project-URL: documentation, https://pychapter10.readthedocs.io/
Project-URL: homepage, https://github.com/atac/pychapter10
Project-URL: repository, https://github.com/atac/pychapter10
